hamsterlib-0.1.0.dist-info/DESCRIPTION.rst
hamsterlib-0.1.0.dist-info/metadata.json
hamsterlib-0.1.0.dist-info/top_level.txt
hamsterlib-0.1.0.dist-info/METADATA
hamsterlib-0.1.0.dist-info/WHEEL
hamsterlib-0.1.0.dist-info/RECORD
hamsterlib/objects.py
hamsterlib/reports.py
hamsterlib/storage.py
hamsterlib/helpers.py
hamsterlib/__init__.py
hamsterlib/lib.py
hamsterlib/backends/__init__.py
hamsterlib/backends/sqlalchemy/objects.py
hamsterlib/backends/sqlalchemy/storage.py
hamsterlib/backends/sqlalchemy/__init__.py
