Metadata-Version: 2.0
Name: hamsterlib
Version: 0.1.0
Summary: A library for common timetracking functionality.
Home-page: https://github.com/elbenfreund/hamsterlib
Author: Eric Goller
Author-email: Elbenfreund@DenkenInEchtzeit.net
License: GPL3
Keywords: hamsterlib
Platform: UNKNOWN
Classifier: Development Status :: 2 - Pre-Alpha
Classifier: Intended Audience :: Developers
Classifier: License :: OSI Approved :: GNU General Public License v3 (GPLv3)
Classifier: Natural Language :: English
Classifier: Programming Language :: Python :: 2
Classifier: Programming Language :: Python :: 2.7
Classifier: Programming Language :: Python :: 3
Classifier: Programming Language :: Python :: 3.4
Requires-Dist: future
Requires-Dist: sqlalchemy
Requires-Dist: icalendar
